<?xml version="1.0" encoding="UTF-8" standalone="yes"?>
<p:sld xmlns:a="http://schemas.openxmlformats.org/drawingml/2006/main" xmlns:r="http://schemas.openxmlformats.org/officeDocument/2006/relationships" xmlns:p="http://schemas.openxmlformats.org/presentationml/2006/main"><p:cSld><p:spTree><p:nvGrpSpPr><p:cNvPr id="1" name="Shape 518"/><p:cNvGrpSpPr/><p:nvPr/></p:nvGrpSpPr><p:grpSpPr><a:xfrm><a:off x="0" y="0"/><a:ext cx="0" cy="0"/><a:chOff x="0" y="0"/><a:chExt cx="0" cy="0"/></a:xfrm></p:grpSpPr><p:pic><p:nvPicPr><p:cNvPr id="3" name="Google Shape;435;p35" descr="Picture 2"><a:extLst><a:ext uri="{FF2B5EF4-FFF2-40B4-BE49-F238E27FC236}"><a16:creationId xmlns:a16="http://schemas.microsoft.com/office/drawing/2014/main" id="{E7CD012C-0705-F141-95B2-38C91FE8C9BD}"/></a:ext></a:extLst></p:cNvPr><p:cNvPicPr preferRelativeResize="0"/><p:nvPr/></p:nvPicPr><p:blipFill rotWithShape="1"><a:blip r:embed="rId3"><a:alphaModFix/></a:blip><a:srcRect/><a:stretch/></p:blipFill><p:spPr><a:xfrm><a:off x="-3894" y="-28242"/><a:ext cx="12364590" cy="6886242"/></a:xfrm><a:prstGeom prst="rect"><a:avLst/></a:prstGeom><a:noFill/><a:ln><a:noFill/></a:ln></p:spPr></p:pic><p:pic><p:nvPicPr><p:cNvPr id="520" name="Google Shape;520;p40" descr="Picture 7"/><p:cNvPicPr preferRelativeResize="0"/><p:nvPr/></p:nvPicPr><p:blipFill rotWithShape="1"><a:blip r:embed="rId4"><a:alphaModFix/></a:blip><a:srcRect/><a:stretch/></p:blipFill><p:spPr><a:xfrm flipH="1"><a:off x="9935965" y="-633869"/><a:ext cx="2180800" cy="1500685"/></a:xfrm><a:prstGeom prst="rect"><a:avLst/></a:prstGeom><a:noFill/><a:ln><a:noFill/></a:ln></p:spPr></p:pic><p:sp><p:nvSpPr><p:cNvPr id="522" name="Google Shape;522;p40"/><p:cNvSpPr txBox="1"/><p:nvPr/></p:nvSpPr><p:spPr><a:xfrm><a:off x="575030" y="153553"/><a:ext cx="7650800" cy="571600"/></a:xfrm><a:prstGeom prst="rect"><a:avLst/></a:prstGeom><a:noFill/><a:ln><a:noFill/></a:ln></p:spPr><p:txBody><a:bodyPr spcFirstLastPara="1" wrap="square" lIns="121900" tIns="121900" rIns="121900" bIns="121900" anchor="t" anchorCtr="0"><a:noAutofit/></a:bodyPr><a:lstStyle/><a:p><a:pPr><a:buSzPts val="1700"/></a:pPr><a:r><a:rPr lang="fr-FR" sz="2267" b="1"><a:solidFill><a:srgbClr val="FFFFFF"/></a:solidFill></a:rPr><a:t>Le bal des Projets à Esprit : Un événement phare</a:t></a:r><a:endParaRPr sz="2267" b="1"><a:solidFill><a:srgbClr val="FFFFFF"/></a:solidFill></a:endParaRPr></a:p><a:p><a:pPr><a:buSzPts val="1700"/></a:pPr><a:endParaRPr sz="2267" b="1"><a:solidFill><a:srgbClr val="FFFFFF"/></a:solidFill></a:endParaRPr></a:p></p:txBody></p:sp><p:sp><p:nvSpPr><p:cNvPr id="523" name="Google Shape;523;p40"/><p:cNvSpPr txBox="1"/><p:nvPr/></p:nvSpPr><p:spPr><a:xfrm><a:off x="665033" y="1011367"/><a:ext cx="7772400" cy="595059"/></a:xfrm><a:prstGeom prst="rect"><a:avLst/></a:prstGeom><a:noFill/><a:ln><a:noFill/></a:ln></p:spPr><p:txBody><a:bodyPr spcFirstLastPara="1" wrap="square" lIns="121900" tIns="121900" rIns="121900" bIns="121900" anchor="t" anchorCtr="0"><a:spAutoFit/></a:bodyPr><a:lstStyle/><a:p><a:pPr><a:buSzPts val="1700"/></a:pPr><a:endParaRPr sz="2267" b="1"><a:solidFill><a:srgbClr val="FFFFFF"/></a:solidFill></a:endParaRPr></a:p></p:txBody></p:sp><p:sp><p:nvSpPr><p:cNvPr id="524" name="Google Shape;524;p40"/><p:cNvSpPr txBox="1"/><p:nvPr/></p:nvSpPr><p:spPr><a:xfrm><a:off x="111801" y="1308970"/><a:ext cx="12077023" cy="4548897"/></a:xfrm><a:prstGeom prst="rect"><a:avLst/></a:prstGeom><a:noFill/><a:ln><a:noFill/></a:ln></p:spPr><p:txBody><a:bodyPr spcFirstLastPara="1" wrap="square" lIns="121900" tIns="121900" rIns="121900" bIns="121900" anchor="t" anchorCtr="0"><a:spAutoFit/></a:bodyPr><a:lstStyle/><a:p><a:pPr marL="608965" indent="-443865" algn="just"><a:lnSpc><a:spcPct val="190000"/></a:lnSpc><a:buClr><a:srgbClr val="434343"/></a:buClr><a:buSzPts val="1650"/><a:buFont typeface="Arial"/><a:buChar char="●"/></a:pPr><a:r><a:rPr lang="fr-FR" sz="2200"><a:solidFill><a:srgbClr val="434343"/></a:solidFill></a:rPr><a:t>Adopté depuis 2012, l’apprentissage par projet est l’un des pivots de la pédagogie innovante qui singularise ESPRIT. Les projets académiques réalisés sont d’un niveau suffisamment élevé et professionnel pour être visibles et reconnus. </a:t></a:r><a:r><a:rPr lang="fr-FR" sz="2200" b="1"><a:solidFill><a:srgbClr val="434343"/></a:solidFill></a:rPr><a:t>Le Bal des projets </a:t></a:r><a:r><a:rPr lang="fr-FR" sz="2200"><a:solidFill><a:srgbClr val="434343"/></a:solidFill></a:rPr><a:t>vient alors couronner chaque année en valorisant le palmarès des projets des étudiants.</a:t></a:r><a:endParaRPr lang="en-US" sz="2200"><a:solidFill><a:srgbClr val="434343"/></a:solidFill></a:endParaRPr></a:p><a:p><a:pPr marL="608965" algn="just"><a:lnSpc><a:spcPct val="190000"/></a:lnSpc><a:spcBef><a:spcPts val="1467"/></a:spcBef><a:buSzPts val="150"/></a:pPr><a:endParaRPr sz="200"><a:solidFill><a:srgbClr val="434343"/></a:solidFill></a:endParaRPr></a:p><a:p><a:pPr marL="608965" indent="-443865" algn="just"><a:lnSpc><a:spcPct val="190000"/></a:lnSpc><a:spcBef><a:spcPts val="1467"/></a:spcBef><a:buClr><a:srgbClr val="434343"/></a:buClr><a:buSzPts val="1650"/><a:buFont typeface="Arial"/><a:buChar char="●"/></a:pPr><a:r><a:rPr lang="fr-FR" sz="2200"><a:solidFill><a:srgbClr val="434343"/></a:solidFill></a:rPr><a:t>Des équipes d’étudiants, toutes filières et tous niveaux confondus participent chaque année au bal des projets, en présentant leurs projets.</a:t></a:r><a:endParaRPr sz="2200"><a:solidFill><a:srgbClr val="434343"/></a:solidFill></a:endParaRPr></a:p></p:txBody></p:sp><p:sp><p:nvSpPr><p:cNvPr id="525" name="Google Shape;525;p40"/><p:cNvSpPr txBox="1"><a:spLocks noGrp="1"/></p:cNvSpPr><p:nvPr><p:ph type="sldNum" idx="12"/></p:nvPr></p:nvSpPr><p:spPr><a:xfrm><a:off x="11020256" y="6496501"/><a:ext cx="360797" cy="276959"/></a:xfrm><a:prstGeom prst="rect"><a:avLst/></a:prstGeom><a:noFill/><a:ln><a:noFill/></a:ln></p:spPr><p:txBody><a:bodyPr spcFirstLastPara="1" wrap="square" lIns="45700" tIns="45700" rIns="45700" bIns="45700" anchor="ctr" anchorCtr="0"><a:spAutoFit/></a:bodyPr><a:lstStyle/><a:p><a:fld id="{00000000-1234-1234-1234-123412341234}" type="slidenum"><a:rPr lang="fr-FR"/><a:pPr/><a:t>30</a:t></a:fld><a:endParaRPr/></a:p></p:txBody></p:sp><p:pic><p:nvPicPr><p:cNvPr id="5" name="Google Shape;437;p35" descr="A red triangle on a black background&#xA;&#xA;Description automatically generated"><a:extLst><a:ext uri="{FF2B5EF4-FFF2-40B4-BE49-F238E27FC236}"><a16:creationId xmlns:a16="http://schemas.microsoft.com/office/drawing/2014/main" id="{230E1824-8165-CC59-526F-D8A18079885D}"/></a:ext></a:extLst></p:cNvPr><p:cNvPicPr preferRelativeResize="0"/><p:nvPr/></p:nvPicPr><p:blipFill rotWithShape="1"><a:blip r:embed="rId5"><a:alphaModFix/></a:blip><a:srcRect/><a:stretch/></p:blipFill><p:spPr><a:xfrm><a:off x="0" y="142853"/><a:ext cx="780427" cy="579781"/></a:xfrm><a:prstGeom prst="rect"><a:avLst/></a:prstGeom><a:noFill/><a:ln><a:noFill/></a:ln></p:spPr></p:pic><p:pic><p:nvPicPr><p:cNvPr id="7" name="Google Shape;439;p35"><a:extLst><a:ext uri="{FF2B5EF4-FFF2-40B4-BE49-F238E27FC236}"><a16:creationId xmlns:a16="http://schemas.microsoft.com/office/drawing/2014/main" id="{18CEFC92-5043-1F0D-6611-894914DD7FEF}"/></a:ext></a:extLst></p:cNvPr><p:cNvPicPr preferRelativeResize="0"/><p:nvPr/></p:nvPicPr><p:blipFill rotWithShape="1"><a:blip r:embed="rId6"><a:alphaModFix/></a:blip><a:srcRect/><a:stretch/></p:blipFill><p:spPr><a:xfrm><a:off x="9965100" y="6283412"/><a:ext cx="1087675" cy="394000"/></a:xfrm><a:prstGeom prst="rect"><a:avLst/></a:prstGeom><a:noFill/><a:ln><a:noFill/></a:ln></p:spPr></p:pic></p:spTree><p:extLst><p:ext uri="{BB962C8B-B14F-4D97-AF65-F5344CB8AC3E}"><p14:creationId xmlns:p14="http://schemas.microsoft.com/office/powerpoint/2010/main" val="2143359916"/></p:ext></p:extLst></p:cSld><p:clrMapOvr><a:masterClrMapping/></p:clrMapOvr></p:sld>