<?xml version="1.0" encoding="UTF-8" standalone="yes"?>
<p:sld xmlns:a="http://schemas.openxmlformats.org/drawingml/2006/main" xmlns:r="http://schemas.openxmlformats.org/officeDocument/2006/relationships" xmlns:p="http://schemas.openxmlformats.org/presentationml/2006/main"><p:cSld><p:spTree><p:nvGrpSpPr><p:cNvPr id="1" name="Shape 296"/><p:cNvGrpSpPr/><p:nvPr/></p:nvGrpSpPr><p:grpSpPr><a:xfrm><a:off x="0" y="0"/><a:ext cx="0" cy="0"/><a:chOff x="0" y="0"/><a:chExt cx="0" cy="0"/></a:xfrm></p:grpSpPr><p:pic><p:nvPicPr><p:cNvPr id="297" name="Google Shape;297;p27" descr="Picture 2"/><p:cNvPicPr preferRelativeResize="0"/><p:nvPr/></p:nvPicPr><p:blipFill rotWithShape="1"><a:blip r:embed="rId3"><a:alphaModFix/></a:blip><a:srcRect/><a:stretch/></p:blipFill><p:spPr><a:xfrm><a:off x="-163901" y="-173612"/><a:ext cx="12524598" cy="6886241"/></a:xfrm><a:prstGeom prst="rect"><a:avLst/></a:prstGeom><a:noFill/><a:ln><a:noFill/></a:ln></p:spPr></p:pic><p:pic><p:nvPicPr><p:cNvPr id="298" name="Google Shape;298;p27" descr="Picture 7"/><p:cNvPicPr preferRelativeResize="0"/><p:nvPr/></p:nvPicPr><p:blipFill rotWithShape="1"><a:blip r:embed="rId4"><a:alphaModFix/></a:blip><a:srcRect/><a:stretch/></p:blipFill><p:spPr><a:xfrm flipH="1"><a:off x="10857903" y="-143663"/><a:ext cx="2000231" cy="1376435"/></a:xfrm><a:prstGeom prst="rect"><a:avLst/></a:prstGeom><a:noFill/><a:ln><a:noFill/></a:ln></p:spPr></p:pic><p:pic><p:nvPicPr><p:cNvPr id="299" name="Google Shape;299;p27"/><p:cNvPicPr preferRelativeResize="0"/><p:nvPr/></p:nvPicPr><p:blipFill rotWithShape="1"><a:blip r:embed="rId5"><a:alphaModFix/></a:blip><a:srcRect/><a:stretch/></p:blipFill><p:spPr><a:xfrm><a:off x="0" y="142853"/><a:ext cx="780427" cy="579781"/></a:xfrm><a:prstGeom prst="rect"><a:avLst/></a:prstGeom><a:noFill/><a:ln><a:noFill/></a:ln></p:spPr></p:pic><p:sp><p:nvSpPr><p:cNvPr id="300" name="Google Shape;300;p27"/><p:cNvSpPr txBox="1"><a:spLocks noGrp="1"/></p:cNvSpPr><p:nvPr><p:ph type="sldNum" idx="12"/></p:nvPr></p:nvSpPr><p:spPr><a:xfrm><a:off x="11089821" y="6404293"/><a:ext cx="264000" cy="276900"/></a:xfrm><a:prstGeom prst="rect"><a:avLst/></a:prstGeom><a:noFill/><a:ln><a:noFill/></a:ln></p:spPr><p:txBody><a:bodyPr spcFirstLastPara="1" wrap="square" lIns="45700" tIns="45700" rIns="45700" bIns="45700" anchor="ctr" anchorCtr="0"><a:spAutoFit/></a:bodyPr><a:lstStyle/><a:p><a:pPr marL="0" lvl="0" indent="0" algn="r" rtl="0"><a:spcBef><a:spcPts val="0"/></a:spcBef><a:spcAft><a:spcPts val="0"/></a:spcAft><a:buClr><a:srgbClr val="888888"/></a:buClr><a:buSzPts val="1200"/><a:buFont typeface="Calibri"/><a:buNone/></a:pPr><a:fld id="{00000000-1234-1234-1234-123412341234}" type="slidenum"><a:rPr lang="fr-FR"/><a:t>20</a:t></a:fld><a:endParaRPr/></a:p></p:txBody></p:sp><p:pic><p:nvPicPr><p:cNvPr id="301" name="Google Shape;301;p27"/><p:cNvPicPr preferRelativeResize="0"/><p:nvPr/></p:nvPicPr><p:blipFill rotWithShape="1"><a:blip r:embed="rId6"><a:alphaModFix/></a:blip><a:srcRect/><a:stretch/></p:blipFill><p:spPr><a:xfrm><a:off x="9965100" y="6283412"/><a:ext cx="1087675" cy="394000"/></a:xfrm><a:prstGeom prst="rect"><a:avLst/></a:prstGeom><a:noFill/><a:ln><a:noFill/></a:ln></p:spPr></p:pic><p:sp><p:nvSpPr><p:cNvPr id="304" name="Google Shape;304;p27"/><p:cNvSpPr txBox="1"><a:spLocks noGrp="1"/></p:cNvSpPr><p:nvPr><p:ph type="title"/></p:nvPr></p:nvSpPr><p:spPr><a:xfrm><a:off x="780427" y="-131333"/><a:ext cx="9809400" cy="1246901"/></a:xfrm><a:prstGeom prst="rect"><a:avLst/></a:prstGeom><a:noFill/><a:ln><a:noFill/></a:ln></p:spPr><p:txBody><a:bodyPr spcFirstLastPara="1" wrap="square" lIns="91425" tIns="45700" rIns="91425" bIns="45700" anchor="ctr" anchorCtr="0"><a:noAutofit/></a:bodyPr><a:lstStyle/><a:p><a:pPr marL="0" lvl="0" indent="0" algn="ctr" rtl="0"><a:lnSpc><a:spcPct val="100000"/></a:lnSpc><a:spcBef><a:spcPts val="0"/></a:spcBef><a:spcAft><a:spcPts val="0"/></a:spcAft><a:buSzPts val="1400"/><a:buNone/></a:pPr><a:r><a:rPr lang="fr-FR"/><a:t>Sujets PIDEV</a:t></a:r><a:endParaRPr/></a:p></p:txBody></p:sp><p:sp><p:nvSpPr><p:cNvPr id="305" name="Google Shape;305;p27"/><p:cNvSpPr/><p:nvPr/></p:nvSpPr><p:spPr><a:xfrm><a:off x="650175" y="2519394"/><a:ext cx="11321370" cy="750114"/></a:xfrm><a:custGeom><a:avLst/><a:gdLst/><a:ahLst/><a:cxnLst/><a:rect l="l" t="t" r="r" b="b"/><a:pathLst><a:path w="21600" h="21600" extrusionOk="0"><a:moveTo><a:pt x="0" y="0"/></a:moveTo><a:lnTo><a:pt x="21600" y="0"/></a:lnTo><a:lnTo><a:pt x="21600" y="21599"/></a:lnTo><a:lnTo><a:pt x="0" y="21599"/></a:lnTo><a:lnTo><a:pt x="0" y="0"/></a:lnTo><a:close/></a:path></a:pathLst></a:custGeom><a:noFill/><a:ln><a:noFill/></a:ln></p:spPr><p:txBody><a:bodyPr spcFirstLastPara="1" wrap="square" lIns="35700" tIns="35700" rIns="35700" bIns="35700" anchor="ctr" anchorCtr="0"><a:noAutofit/></a:bodyPr><a:lstStyle/><a:p><a:pPr marL="276810" marR="0" lvl="0" indent="-276810" algn="l" rtl="0"><a:lnSpc><a:spcPct val="100000"/></a:lnSpc><a:spcBef><a:spcPts val="0"/></a:spcBef><a:spcAft><a:spcPts val="0"/></a:spcAft><a:buClr><a:schemeClr val="dk1"/></a:buClr><a:buSzPts val="1650"/><a:buFont typeface="Arial"/><a:buChar char="•"/></a:pPr><a:r><a:rPr lang="fr-FR" sz="2200" b="0" i="0" u="none" strike="noStrike" cap="none"><a:solidFill><a:schemeClr val="dk1"/></a:solidFill><a:latin typeface="Calibri" panose="020F0502020204030204" pitchFamily="34" charset="0"/><a:ea typeface="Calibri" panose="020F0502020204030204" pitchFamily="34" charset="0"/><a:cs typeface="Calibri" panose="020F0502020204030204" pitchFamily="34" charset="0"/><a:sym typeface="Arial"/></a:rPr><a:t>Choix du sujet selon les thématiques proposées.</a:t></a:r><a:endParaRPr><a:latin typeface="Calibri" panose="020F0502020204030204" pitchFamily="34" charset="0"/><a:ea typeface="Calibri" panose="020F0502020204030204" pitchFamily="34" charset="0"/><a:cs typeface="Calibri" panose="020F0502020204030204" pitchFamily="34" charset="0"/></a:endParaRPr></a:p><a:p><a:pPr marL="276810" marR="0" lvl="0" indent="-276810" algn="l" rtl="0"><a:lnSpc><a:spcPct val="100000"/></a:lnSpc><a:spcBef><a:spcPts val="0"/></a:spcBef><a:spcAft><a:spcPts val="0"/></a:spcAft><a:buClr><a:schemeClr val="dk1"/></a:buClr><a:buSzPts val="1650"/><a:buFont typeface="Arial"/><a:buChar char="•"/></a:pPr><a:r><a:rPr lang="fr-FR" sz="2200" b="0" i="0" u="none" strike="noStrike" cap="none"><a:solidFill><a:schemeClr val="dk1"/></a:solidFill><a:latin typeface="Calibri" panose="020F0502020204030204" pitchFamily="34" charset="0"/><a:ea typeface="Calibri" panose="020F0502020204030204" pitchFamily="34" charset="0"/><a:cs typeface="Calibri" panose="020F0502020204030204" pitchFamily="34" charset="0"/><a:sym typeface="Arial"/></a:rPr><a:t>Les sujets doivent être différents dans une même classe et dans une même thématique</a:t></a:r></a:p><a:p><a:pPr marL="276810" marR="0" lvl="0" indent="-276810" algn="l" rtl="0"><a:lnSpc><a:spcPct val="100000"/></a:lnSpc><a:spcBef><a:spcPts val="0"/></a:spcBef><a:spcAft><a:spcPts val="0"/></a:spcAft><a:buClr><a:schemeClr val="dk1"/></a:buClr><a:buSzPts val="1650"/><a:buFont typeface="Arial"/><a:buChar char="•"/></a:pPr><a:r><a:rPr lang="fr-FR" sz="2200"><a:solidFill><a:schemeClr val="dk1"/></a:solidFill><a:latin typeface="Calibri" panose="020F0502020204030204" pitchFamily="34" charset="0"/><a:ea typeface="Calibri" panose="020F0502020204030204" pitchFamily="34" charset="0"/><a:cs typeface="Calibri" panose="020F0502020204030204" pitchFamily="34" charset="0"/></a:rPr><a:t>Les sujets doivent traiter au moins l’un des ODD </a:t></a:r></a:p></p:txBody></p:sp><p:pic><p:nvPicPr><p:cNvPr id="3" name="Image 2" descr="Une image contenant texte, capture d’écran, logo, Police&#xA;&#xA;Description générée automatiquement"><a:extLst><a:ext uri="{FF2B5EF4-FFF2-40B4-BE49-F238E27FC236}"><a16:creationId xmlns:a16="http://schemas.microsoft.com/office/drawing/2014/main" id="{E94E38D3-A9B5-FD65-CE2C-E238475A4306}"/></a:ext></a:extLst></p:cNvPr><p:cNvPicPr><a:picLocks noChangeAspect="1"/></p:cNvPicPr><p:nvPr/></p:nvPicPr><p:blipFill><a:blip r:embed="rId7"/><a:stretch><a:fillRect/></a:stretch></p:blipFill><p:spPr><a:xfrm><a:off x="2462024" y="3789130"/><a:ext cx="6198111" cy="2186575"/></a:xfrm><a:prstGeom prst="rect"><a:avLst/></a:prstGeom></p:spPr></p:pic></p:spTree></p:cSld><p:clrMapOvr><a:masterClrMapping/></p:clrMapOvr></p:sld>